qnngds-4.1.1.dist-info/METADATA
qnngds-4.1.1.dist-info/WHEEL
qnngds-4.1.1.dist-info/entry_points.txt
qnngds-4.1.1.dist-info/licenses/LICENSE.txt
qnngds/__init__.py
qnngds/circuits.py
qnngds/design.py
qnngds/devices/__init__.py
qnngds/devices/htron.py
qnngds/devices/nanowire.py
qnngds/devices/ntron.py
qnngds/devices/resistor.py
qnngds/devices/resonator.py
qnngds/devices/snspd.py
qnngds/experiments.py
qnngds/geometries.py
qnngds/tests.py
qnngds/utilities.py
qnngds-4.1.1.dist-info/RECORD
