Metadata-Version: 2.1
Name: qnngds
Version: 4.1.1
Summary: The QNN library for creating gds files
Keywords: phidl,nanowire_electronics,nanofabrication,gds
Author-Email: "A. Jacquillat" <audrey01@mit.edu>, "A. Jacquillat" <audrey.jacquillat@gmail.com>, "R. Foster" <reedf@mit.edu>, "E. Batson" <emmabat@mit.edu>, "O. Medeiros" <omedeiro@mit.edu>, "A. Simon" <alejansi@mit.edu>
Maintainer-Email: "A. Jacquillat" <audrey01@mit.edu>, "R. Foster" <reedf@mit.edu>
License: Copyright (c) 2016 The Python Packaging Authority (PyPA)
Classifier: Programming Language :: Python :: 3
Classifier: License :: OSI Approved :: MIT License
Classifier: Operating System :: OS Independent
Classifier: Intended Audience :: Science/Research
Classifier: Topic :: Scientific/Engineering
Project-URL: Homepage, https://github.com/qnngroup/qnngds
Project-URL: Issues, https://github.com/qnngroup/qnngds/issues
Project-URL: Documentation, https://qnngds.readthedocs.io/en/latest/
Project-URL: How_to_contribute, https://qnngds-dev.readthedocs.io/en/latest/
Requires-Python: >=3.9
Requires-Dist: phidl
Requires-Dist: scipy
